odoo/addons/agreement_operating_unit/README.rst
odoo/addons/agreement_operating_unit/__init__.py
odoo/addons/agreement_operating_unit/__manifest__.py
odoo/addons/agreement_operating_unit/i18n/agreement_operating_unit.pot
odoo/addons/agreement_operating_unit/i18n/es.po
odoo/addons/agreement_operating_unit/i18n/fr.po
odoo/addons/agreement_operating_unit/i18n/it.po
odoo/addons/agreement_operating_unit/i18n/pt.po
odoo/addons/agreement_operating_unit/models/__init__.py
odoo/addons/agreement_operating_unit/models/agreement.py
odoo/addons/agreement_operating_unit/models/agreement_serviceprofile.py
odoo/addons/agreement_operating_unit/readme/CONTRIBUTORS.rst
odoo/addons/agreement_operating_unit/readme/CREDITS.rst
odoo/addons/agreement_operating_unit/readme/DESCRIPTION.rst
odoo/addons/agreement_operating_unit/readme/USAGE.rst
odoo/addons/agreement_operating_unit/security/aggreement_security.xml
odoo/addons/agreement_operating_unit/static/description/icon.png
odoo/addons/agreement_operating_unit/static/description/index.html
odoo/addons/agreement_operating_unit/tests/__init__.py
odoo/addons/agreement_operating_unit/tests/test_agreement_operating_unit.py
odoo/addons/agreement_operating_unit/views/agreement.xml
odoo/addons/agreement_operating_unit/views/agreement_serviceprofile.xml
odoo14_addon_agreement_operating_unit-14.0.1.0.1.dev12.dist-info/METADATA
odoo14_addon_agreement_operating_unit-14.0.1.0.1.dev12.dist-info/WHEEL
odoo14_addon_agreement_operating_unit-14.0.1.0.1.dev12.dist-info/top_level.txt
odoo14_addon_agreement_operating_unit-14.0.1.0.1.dev12.dist-info/RECORD
